kuptoo_encoders/encoders/__init__.py
kuptoo_encoders/encoders/word2vec_from_dict_encoder.py
kuptoo_encoders/encoders/word_2_measure.py
kuptoo_encoders/encoders/word_2_ner_encoder.py
kuptoo_encoders/encoders/word_2_tag_encoder.py
kuptoo_encoders/encoders/__pycache__/__init__.cpython-37.pyc
kuptoo_encoders/encoders/utils/math.py
kuptoo_encoders/encoders/utils/padding.py
kuptoo_encoders/encoders/utils/__pycache__/math.cpython-37.pyc
kuptoo_encoders/encoders/utils/__pycache__/padding.cpython-37.pyc
kuptoo_encoders-0.1.4.dist-info/METADATA
kuptoo_encoders-0.1.4.dist-info/WHEEL
kuptoo_encoders-0.1.4.dist-info/top_level.txt
kuptoo_encoders-0.1.4.dist-info/RECORD
